fuzzyrust-0.3.1.dist-info/METADATA
fuzzyrust-0.3.1.dist-info/WHEEL
fuzzyrust-0.3.1.dist-info/licenses/LICENSE
fuzzyrust/__init__.py
fuzzyrust/__init__.pyi
fuzzyrust/_core.cpython-310-darwin.so
fuzzyrust/_plugin/__init__.py
fuzzyrust/_utils.py
fuzzyrust/batch.py
fuzzyrust/batch.pyi
fuzzyrust/enums.py
fuzzyrust/expr.py
fuzzyrust/index.py
fuzzyrust/polars/__init__.py
fuzzyrust/polars/__init__.pyi
fuzzyrust/py.typed
fuzzyrust-0.3.1.dist-info/RECORD
