Metadata-Version: 2.4
Name: fuzzyrust
Version: 0.3.1
Classifier: Development Status :: 4 - Beta
Classifier: Intended Audience :: Developers
Classifier: License :: OSI Approved :: BSD License
Classifier: Operating System :: OS Independent
Classifier: Programming Language :: Python :: 3
Classifier: Programming Language :: Python :: 3.9
Classifier: Programming Language :: Python :: 3.10
Classifier: Programming Language :: Python :: 3.11
Classifier: Programming Language :: Python :: 3.12
Classifier: Programming Language :: Python :: 3.13
Classifier: Programming Language :: Rust
Classifier: Topic :: Text Processing
Classifier: Topic :: Text Processing :: Indexing
Classifier: Typing :: Typed
Requires-Dist: polars>=1.36.1
Requires-Dist: maturin>=1.7,<2.0 ; extra == 'dev'
Requires-Dist: pytest>=8.3.5 ; extra == 'dev'
Requires-Dist: pytest-benchmark>=4.0 ; extra == 'dev'
Requires-Dist: hypothesis>=6.0 ; extra == 'dev'
Requires-Dist: ruff>=0.14.10 ; extra == 'dev'
Requires-Dist: pytest-cov>=7.0.0 ; extra == 'dev'
Requires-Dist: pre-commit>=4.3.0 ; extra == 'dev'
Requires-Dist: mkdocs>=1.6.1 ; extra == 'dev'
Requires-Dist: mkdocs-material>=9.7.1 ; extra == 'dev'
Requires-Dist: jellyfish>=1.2.1 ; extra == 'benchmarks'
Requires-Dist: python-levenshtein>=0.27.1 ; extra == 'benchmarks'
Requires-Dist: rapidfuzz>=3.13.0 ; extra == 'benchmarks'
Requires-Dist: thefuzz>=0.22.1 ; extra == 'benchmarks'
Requires-Dist: jupyter>=1.1.1 ; extra == 'jupyter'
Requires-Dist: ipykernel>=6.29.0 ; extra == 'jupyter'
Requires-Dist: fuzzyrust[dev,benchmarks,jupyter] ; extra == 'all'
Provides-Extra: dev
Provides-Extra: benchmarks
Provides-Extra: jupyter
Provides-Extra: all
License-File: LICENSE
Summary: High-performance string similarity library for Python, written in Rust
Keywords: fuzzy,string,similarity,search,levenshtein,jaro-winkler
Author-email: Tomislav Suhina <tomislav.suhina@gmail.com>
License: BSD-3-Clause
Requires-Python: >=3.9
Project-URL: Homepage, https://github.com/tsuhina/fuzzyrust
Project-URL: Documentation, https://github.com/tsuhina/fuzzyrust#readme
Project-URL: Repository, https://github.com/tsuhina/fuzzyrust
Project-URL: Issues, https://github.com/tsuhina/fuzzyrust/issues
